[
  {
    "title": "Nombre del Producto 1",
    "description": "Descripción del Producto",
    "code": "1",
    "price": 19.99,
    "stock": 100,
    "category": "URL de la imagen del producto",
    "id": 1
  },
  {
    "title": "Nombre del Producto 2",
    "description": "Descripción del Producto",
    "code": "2",
    "price": 19.99,
    "stock": 100,
    "category": "URL de la imagen del producto",
    "id": 2
  },
  {
    "title": "Nombre del Producto 3",
    "description": "Descripción del Producto",
    "code": "3",
    "price": 19.99,
    "stock": 100,
    "category": "URL de la imagen del producto",
    "id": 3
  },
  {
    "title": "Nombre del Producto 4",
    "description": "Descripción del Producto",
    "code": "4",
    "price": 19.99,
    "stock": 100,
    "category": "URL de la imagen del producto",
    "id": 4
  },
  {
    "title": "Nombre del Producto 5",
    "description": "Descripción del Producto",
    "code": "5",
    "price": 19.99,
    "stock": 100,
    "category": "URL de la imagen del producto",
    "id": 5
  },
  {
    "title": "Nombre del Producto 6",
    "description": "Descripción del Producto",
    "code": "6",
    "price": 19.99,
    "stock": 100,
    "category": "URL de la imagen del producto",
    "id": 6
  }
]